{"id":600,"title":"Ethereum purpose allocation for Deterministic Wallets","description":"This EIP defines a logical hierarchy for deterministic wallets based on [BIP32](https://github.com/bitcoin/bips/blob/master/bip-0032.mediawiki), the purpose scheme defined in [BIP43](https://github.com/bitcoin/bips/blob/master/bip-0043.medi","authors":["Nick Johnson","Micah Zoltu"],"status":"Final","type":"Standards Track","category":"ERC","bucket":"wallet","created":"2017-04-13T00:00:00.000Z","requires":[],"replaces":[],"supersededBy":[],"tags":[],"body":"\n## Abstract\nThis EIP defines a logical hierarchy for deterministic wallets based on [BIP32](https://github.com/bitcoin/bips/blob/master/bip-0032.mediawiki), the purpose scheme defined in [BIP43](https://github.com/bitcoin/bips/blob/master/bip-0043.mediawiki) and [this proposed change to BIP43](https://github.com/bitcoin/bips/pull/523).\n\nThis EIP is a particular application of BIP43.\n\n## Motivation\nBecause Ethereum is based on account balances rather than UTXO, the hierarchy defined by BIP44 is poorly suited. As a result, several competing derivation path strategies have sprung up for deterministic wallets, resulting in inter-client incompatibility. This BIP seeks to provide a path to standardise this in a fashion better suited to Ethereum's unique requirements.\n\n## Specification\nWe define the following 2 levels in BIP32 path:\n\n<pre>\nm / purpose' / subpurpose' / EIP'\n</pre>\n\nApostrophe in the path indicates that BIP32 hardened derivation is used.\n\nEach level has a special meaning, described in the chapters below.\n\n### Purpose\n\nPurpose is set to 43, as documented in [this proposed change to BIP43](https://github.com/bitcoin/bips/pull/523).\n\nThe purpose field indicates that this path is for a non-bitcoin cryptocurrency.\n\nHardened derivation is used at this level.\n\n### Subpurpose\nSubpurpose is set to 60, the SLIP-44 code for Ethereum.\n\nHardened derivation is used at this level.\n\n### EIP\nEIP is set to the EIP number specifying the remainder of the BIP32 derivation path. This permits new Ethereum-focused applications of deterministic wallets without needing to interface with the BIP process.\n\nHardened derivation is used at this level.\n\n## Rationale\nThe existing convention is to use the 'Ethereum' coin type, leading to paths starting with `m/44'/60'/*`. Because this still assumes a UTXO-based coin, we contend that this is a poor fit, resulting in standardisation, usability, and security compromises. As a result, we are making the above proposal to define an entirely new hierarchy for Ethereum-based chains.\n\n## Backwards Compatibility\nThe introduction of another derivation path requires existing software to add support for this scheme in addition to any existing schemes. Given the already confused nature of wallet derivation paths in Ethereum, we anticipate this will cause relatively little additional disruption, and has the potential to improve matters significantly in the long run.\n\n## Test Cases\nTBD\n\n## Implementation\nNone yet.\n\n## References\n[This discussion on derivation paths](https://github.com/ethereum/EIPs/issues/84)\n\n## Copyright\nCopyright and related rights waived via [CC0](../LICENSE.md).\n","rawUrl":"https://raw.githubusercontent.com/ethereum/EIPs/master/EIPS/eip-600.md","githubUrl":"https://github.com/ethereum/EIPs/blob/master/EIPS/eip-600.md","officialUrl":"https://eips.ethereum.org/EIPS/eip-600","views":0,"favorites":0,"popularity":40}