{"id":8197,"title":"Cryptographically Agile Transactions","description":"Cryptographically Agile Transaction format separating signature from transaction body","authors":["Danno Ferrin","Ron Kahat"],"status":"Draft","type":"Standards Track","category":"Core","bucket":"infrastructure","created":"2025-03-04T00:00:00.000Z","requires":[1559,2718,2930,4844,7702],"replaces":[],"supersededBy":[],"tags":[],"body":"\n## Abstract\n\nCATX (Cryptographically Agile Transactions) is an [EIP-2718](./eip-2718.md)\ntransaction format that separates the transaction body from its signatures using\na flat structure: `[payload_type, payload_body, (sig_type, sig_body)+]`. This\nenables future migration to post-quantum cryptography without modifying\ntransaction semantics, supports multi-signature payloads resistant to key\nsubstitution attacks using chained signature hashes, and facilitates future\nsupport of zk signature aggregation.\n\n## Motivation\n\nCurrent Ethereum transactions tightly couple body and signature by embedding\nalgorithm-specific fields in the transaction, requiring new transaction types\nfor each signature algorithm. CATX addresses three key concerns:\n\n1. **Post-quantum cryptography adoption**: Signature types are independent of\n   payload types, enabling migration to PQC algorithms without modifying\n   transaction semantics\n2. **Key substitution resistance**: Chained signature hashes prevent key\n   substitution attacks (Fujita et al., 2024) in multi-signature payloads\n3. **ZK signature aggregation**: Trailing signatures can be easily stripped and\n   replaced for aggregation schemes, with the payload body remaining intact for\n   proof generation\n\n## Specification\n\n### Parameters\n\n| Name                 | Description                                          | Value  |\n|----------------------|------------------------------------------------------|--------|\n| `CA_TX_TYPE`         | [EIP-2718](./eip-2718.md) transaction type           | TBD    |\n| `ECDSA_SIG_TYPE`     | ECDSA signature identifier                           | `0x00` |\n| `SET_CODE_AUTH_TYPE` | [EIP-7702](./eip-7702.md) authorization type (MAGIC) | `0x05` |\n\nThis EIP defines the transaction format and encoding rules. The assignment of\n`sig_type` values to specific cryptographic algorithms will be governed by other\nEIPs. The ECDSA signature type (`0x00`) is specified here as the existing\nsignature algorithm—in the event of conflict, the signature type registry EIP\ntakes precedence.\n\n### Transaction Encoding\n\n```\nCA_TX_TYPE || rlp([payload_type, payload_body, (sig_type, sig_body)+])\n```\n\nSignatures are appended as flat alternating `sig_type, sig_body` pairs. The\nnumber of signature pairs required is controlled by the payload (either fixed\nper `payload_type` or determined by fields within `payload_body`). If a\ntransaction does not contain exactly the required number of signatures, the\ntransaction is invalid.\n\n### Payload Types and Data\n\n| Type   | Name                      | Sig Count | payload_body                                                                                                                                         |\n|--------|---------------------------|-----------|------------------------------------------------------------------------------------------------------------------------------------------------------|\n| `0x01` | [EIP-2930](./eip-2930.md) | 1         | `[chain_id, nonce, gas_price, gas_limit, to, value, data, access_list]`                                                                              |\n| `0x02` | [EIP-1559](./eip-1559.md) | 1         | `[chain_id, nonce, max_priority_fee_per_gas, max_fee_per_gas, gas_limit, to, value, data, access_list]`                                              |\n| `0x03` | [EIP-4844](./eip-4844.md) | 1         | `[chain_id, nonce, max_priority_fee_per_gas, max_fee_per_gas, gas_limit, to, value, data, access_list, max_fee_per_blob_gas, blob_versioned_hashes]` |\n| `0x04` | [EIP-7702](./eip-7702.md) | 1         | `[chain_id, nonce, max_priority_fee_per_gas, max_fee_per_gas, gas_limit, to, value, data, access_list, authorization_list]`                          |\n\nLegacy (type 0) transactions are not supported.\n\n`payload_body` corresponds to the signing form of the related transaction types.\nThe referenced EIPs govern the meaning and validation of the fields in their\nrespective payload bodies, except as noted below.\n\n#### [EIP-7702](./eip-7702.md) Authorization List\n\nFor type `0x04` payloads, the `authorization_list` contains CATX-formatted\nauthorization tuples:\n\n```\nauthorization_list = [[SET_CODE_AUTH_TYPE, [chain_id, address, nonce], sig_type, sig_body], ...]\n```\n\nEach authorization follows the same flat structure as the outer transaction: a\ntype byte, a body, and a signature pair. The authorization signature hash is:\n\n```\nauth_hash = keccak256(rlp(SET_CODE_AUTH_TYPE) || rlp([chain_id, address, nonce]))\n```\n\nThe authority address is recovered from the authorization signature using the\nsame address derivation rules as the outer transaction signatures. Authorization\nprocessing follows EIP-7702 semantics.\n\n### Signatures\n\nEach signature consists of a `sig_type, sig_body` pair. `sig_type` is encoded as\nan RLP number. `sig_body` is encoded as an RLP byte string (using either short\nor long string encoding as appropriate for the signature length).\n\nWhen a signature is transmitted with both public key or verification key and\nsignature data, the public key or verification key should be first in the\n`sig_body`. This does not apply to algorithms that support key extraction such\nas ECDSA.\n\nSome proposed transaction types, like Frame\ntransactions ([EIP-8141](./eip-8141.md)), will require multiple signatures\ncommitting to the whole transaction. The payload body controls how many\nsignatures are required.\n\n### Signature Hash\n\nEach signature commits to the payload and all preceding signatures. The hash is\ncomputed as:\n\n```\npayload_commitment = CA_TX_TYPE || rlp(payload_type) || rlp(payload_body)\nsignature_hash(0) = keccak256(payload_commitment)\nsignature_hash(i) = keccak256(payload_commitment\n    || rlp(sig_type_0) || rlp(sig_body_0)\n    || ...\n    || rlp(sig_type_{i-1}) || rlp(sig_body_{i-1}))\n```\n\nWhere `payload_type` is the inner type byte. The `CA_TX_TYPE` prefix in\n`payload_commitment` binds all signatures to the CATX transaction format. Each\nsignature at index `i > 0` additionally includes all preceding `(sig_type,\nsig_body)` pairs, creating an ordered commitment chain.\n\n### Signature Type 0: ECDSA\n\nThe ECDSA signature type (`sig_type = 0x00`, RLP encoded as `0x80`) is specified\nhere for bootstrapping purposes. In the event of conflict for the ECDSA type\ndefinition other specifications prevail.\n\nThe signature body for ECDSA(secp256k1) is defined as:\n\n```\nsig_body = y_parity[1] || r[32] || s[32]\n```\n\nWhere `y_parity` uses 0/1 parity (not legacy `v` values of 27/28); any other\nvalue is invalid. The length of the sig_body is 65 bytes; if it is not 65 bytes,\nthe signature is invalid. Existing rules regarding ECDSA signatures, such as `s`\nbeing in the lower half of the curve order, are observed as well.\n\n### Address Derivation\n\nAddress derivation depends on the signature type.\n\n**ECDSA (0x00)**: Uses the legacy Ethereum address derivation for backwards\ncompatibility:\n\n```\naddress = keccak256(uncompressed_pubkey)[12:32]\n```\n\nWhere `uncompressed_pubkey` is the 64-byte public key (without the `0x04`\nprefix).\n\n**Non-ECDSA signature types**: Include the signature type in the hash.\n\n```python\ndef derive_address(sig_type: uint8, public_key: bytes) -> ExecutionAddress:\n    if sig_type == 0x00:\n        # ECDSA: legacy derivation\n        return keccak256(public_key)[12:32]\n    elif len(public_key) == 63:\n        # Pad 63-byte keys with 0x00 between sig_type and key\n        return keccak256(sig_type || 0x00 || public_key)[12:32]\n    else:\n        return keccak256(sig_type || public_key)[12:32]\n```\n\n### Receipts\n\nThe common receipt formatting is used\n\n```\nCA_TX_TYPE || rlp([status, cumulative_gas_used, logs_bloom, logs])\n```\n\n### Transaction Hash\n\nThe transaction hash is computed as:\n\n```\ntx_hash = keccak256(CA_TX_TYPE || rlp([payload_type, payload_body, sig_type, sig_body, ...]))\n```\n\nThis is the keccak256 hash over the entire encoded transaction.\n\n### Gas Costs\n\nGas costing rules for each payload type are governed by their respective EIPs.\nECDSA signatures impose no additional cost beyond what the referenced EIPs\nalready specify.\n\nEIPs defining new signature types should specify a gas penalty or discount\nrelative to ECDSA to account for the algorithm's verification cost, as well as\nadjustments for signature size differences comparable to calldata costs.\n\n## Rationale\n\n### Separation of Format and Algorithm Registry\n\nThis EIP intentionally limits its scope to the transaction format—encoding,\nsignature hash chaining, and address derivation rules—without establishing a\ncomprehensive signature type registry. Algorithm assignments, `sig_body`\nencoding rules, and gas cost adjustments for new signature types are concerns\nthat evolve independently of the transaction format and are better managed by a\ndedicated registry EIP such as [EIP-7932](./eip-7932.md). The ECDSA type is\nincluded here only to make the format immediately usable; deferring to the\nregistry in case of conflict avoids locking algorithm-specific decisions into\nthe transaction format specification.\n\n### Flat Structure\n\nEnables independent extension of payload types and signature algorithms without\nunneeded RLP nesting structures.\n\n### Payload-Controlled Signature Count\n\nThe payload controls how many signatures are required: either as a fixed count\nper `payload_type` or determined by fields within the `payload_body`. This\nallows payload types to define their own multi-signature semantics (e.g.,\nvariable frame counts in EIP-8141) while ensuring all required signatures are\npresent.\n\n### Trailing vs. Embedded Signatures\n\nThe trailing signature table is for signatures that commit to the entire\ntransaction. EIP-7702 authorization signatures commit to a substructure (the\ndelegation tuple) rather than the entire transaction, so they remain embedded\nwithin the `payload_body` using the same `[type, body, sig_type, sig_body]`\nstructure. This distinction is important: trailing signatures can be stripped\nfor ZK aggregation while embedded signatures are part of the payload semantics.\n\n### CATX-Formatted Authorizations\n\nEIP-7702 authorizations use `SET_CODE_AUTH_TYPE` (`0x05`) as their type byte,\nwhich is the same MAGIC value used in EIP-7702. This means the authorization\nsigning hash `keccak256(0x05 || rlp([chain_id, address, nonce]))` is unchanged\nfrom EIP-7702, and like the outer transaction, the signed data can be obtained\nby slicing the encoded structure rather than re-serializing it.\n`SET_CODE_AUTH_TYPE` serves the same role as `payload_type` in the outer\ntransaction—the signed message can be extracted by slicing the encoded\nauthorization without re-serialization. This also means existing ECDSA EIP-7702\nauthorization signatures can be directly converted into CATX-formatted\nauthorizations without re-signing. If authorization convertibility is not\ndesired, the same chained hashing scheme used for outer signatures could be\napplied to authorization signatures to bind them to the CATX format.\n\n### CATX Signature Domain Separation\n\nThe `CA_TX_TYPE || rlp(payload_type)` construction in `payload_commitment`\navoids signature malleability with non-CATX transaction types. Non-CATX types\nprefix only their own type byte (e.g., `0x02` for EIP-1559) before the RLP\npayload, while CATX prepends the additional `CA_TX_TYPE` byte. This ensures that\na signature produced for a non-CATX transaction cannot be replayed as a CATX\nsignature, and a CATX signature cannot be extracted and used in a non-CATX\ntransaction. Transactions must be re-signed when converting between formats.\n\n### Chained Signature Hashes\n\nThis EIP uses the chained commitment structure first described\nin [EIP-8175](./eip-8175.md). This commits each signature to all prior\nsignatures in the transaction. This provides stronger guarantees than simple\nposition indexing because each signer explicitly endorses the identity and\ncommitment of all preceding signers. The chained hash structure ensures:\n\n- Signature at index 0 signs `hash(payload_commitment)`\n- Signature at index 1 signs `hash(payload_commitment || payload_commitment\n    || rlp(sig_type_0) || rlp(sig_body_0))`\n- Signature at index 2 signs\n  `hash(CA_TX_TYPE || payload_commitment payload_commitment\n    || rlp(sig_type_0) || rlp(sig_body_0)\n    || rlp(sig_type_1) || rlp(sig_body_1))`\n- Signatures cannot be reordered or substituted between positions\n\nFor example, a paymaster agreeing to sponsor a transaction can include the\nsender's signature in its own signing hash, ensuring it only pays for a\ntransaction actually signed by the expected sender. Without chaining, a\npaymaster's signature could be paired with a different sender's signature for\nthe same payload, potentially changing who benefits from the sponsorship.\n\nThis is critical for payload types like EIP-8141 Frame transactions where\nmultiple parties (sender, sponsor) sign the same transaction body but for\ndifferent purposes.\n\n### Legacy Transaction Exclusion\n\nLegacy (type 0) transactions are not supported because payload information is\nencoded in the signature, making it impossible to cleanly separate the body from\nthe signature.\n\n### Address Derivation and Cross-Scheme Collisions\n\nAddress derivation depends on the signature type to prevent cross-scheme\ncollisions. The 63-byte special case inserts a `0x00` padding byte. Without it,\n`keccak256(sig_type || 63_byte_key)` would be 64 bytes—the same length as\nECDSA's `keccak256(64_byte_key)`—creating potential collision risk. This\napproach is consistent with [EIP-7932](./eip-7932.md).\n\n### Reduced Signature Manipulation\n\nThe signature hash uses a byte-slice of the payload instead of a re-written\ncontainer for the payload, simplifying memory management.\n\n## Backwards Compatibility\n\nThis is a new transaction type and does not affect existing\ntypes. [EIP-2930](./eip-2930.md)/[EIP-1559](./eip-1559.md)/[EIP-4844](./eip-4844.md)/[EIP-7702](./eip-7702.md)\ntransactions can be converted to CATX format. The `CA_TX_TYPE` prefix in the\nsignature hash means existing signatures are not directly\ncompatible—transactions must be re-signed for CATX format.\n\n## Security Considerations\n\n### Signature Algorithm Binding\n\nThe `sig_type` field binds each signature to a specific algorithm.\nImplementations MUST verify that the correct algorithm is used for each\nsignature and MUST reject transactions where the signature count does not\nexactly match the count required by the payload. The valid set of signature\ntypes can be updated during hard forks, enabling deprecation of vulnerable\nschemes while keeping existing transaction structures intact.\n\n### Key Substitution Attacks\n\nIn a multi-signature transaction, a key substitution attack (Fujita, Sakai,\nYamashita, & Hanaoka, \"On Key Substitution Attacks against Aggregate Signatures\nand Multi-Signatures,\" IACR ePrint 2024/1728) occurs when one signer's signature\nis replaced or reordered to change the authorization semantics. The chained\nsignature hash structure defends against this: because each signature at index\n`i` commits to all preceding signatures, later signers cryptographically endorse\nthe specific identities of all earlier signers. Replacing an earlier signature\ninvalidates every following signature in the chain, and reordering signatures\nchanges the hash inputs, making the substituted signatures unverifiable.\n\n### Cross-Scheme Address Collisions\n\nNon-ECDSA types use distinct address derivation that includes the\n`sig_type` in the hash input, ensuring that different signature algorithms\nproduce non-overlapping address spaces. This prevents an attacker from\nexploiting a collision between key formats of different algorithms to claim\ncontrol of an address derived under a different scheme.\n\n### CATX Signature Domain Separation\n\nThe `payload_commitment` includes `CA_TX_TYPE` as a prefix before\n`rlp(payload_type)`, ensuring that CATX signatures are not valid for the\ncorresponding non-CATX transaction types and vice versa. A non-CATX EIP-1559\nsignature signs `keccak256(0x02 || rlp([...]))` while a CATX signature for the\nsame payload signs `keccak256(CA_TX_TYPE || 0x02 || rlp([...]))`. This binds all\nCATX signatures—including index 0—to the CATX representation, preventing\ncross-format signature reuse.\n\n### Authorization Signature Malleability\n\nBecause the EIP-7702 authorization signing hash is identical between standard\ntype-4 transactions and CATX transactions, authorization signatures can be\nfreely converted between the two formats. This is intentional and safe—the\nauthorization semantics are identical regardless of the containing transaction\nformat.\n\n## Copyright\n\nCopyright and related rights waived via [CC0](../LICENSE.md).\n","rawUrl":"https://raw.githubusercontent.com/ethereum/EIPs/master/EIPS/eip-8197.md","githubUrl":"https://github.com/ethereum/EIPs/blob/master/EIPS/eip-8197.md","officialUrl":"https://eips.ethereum.org/EIPS/eip-8197","views":0,"favorites":0,"popularity":16}